webclient_helper/__init__.py
webclient_helper/client.py
webclient_helper-0.0.8.dist-info/LICENSE.txt
webclient_helper-0.0.8.dist-info/METADATA
webclient_helper-0.0.8.dist-info/WHEEL
webclient_helper-0.0.8.dist-info/top_level.txt
webclient_helper-0.0.8.dist-info/RECORD
