Metadata-Version: 2.1
Name: webclient-helper
Version: 0.0.8
Summary: Helpful WebClient class to interact with APIs on the web
Home-page: https://github.com/kenjyco/webclient-helper
Author: Ken
Author-email: kenjyco@gmail.com
License: MIT
Download-URL: https://github.com/kenjyco/webclient-helper/tarball/v0.0.8
Keywords: webclient,api,requests,soup,beautifulsoup,lxml,http,rest,helper,kenjyco
Platform: UNKNOWN
Classifier: Development Status :: 3 - Alpha
Classifier: Environment :: Console
Classifier: Environment :: Web Environment
Classifier: Intended Audience :: Developers
Classifier: License :: OSI Approved :: MIT License
Classifier: Operating System :: MacOS :: MacOS X
Classifier: Operating System :: POSIX :: Linux
Classifier: Programming Language :: Python :: 3.5
Classifier: Programming Language :: Python
Classifier: Topic :: Software Development :: Libraries
Classifier: Topic :: Text Processing :: Markup :: HTML
Classifier: Topic :: Text Processing :: Markup :: XML
Classifier: Topic :: Utilities
License-File: LICENSE.txt
Requires-Dist: fs-helper
Requires-Dist: input-helper
Requires-Dist: requests
Requires-Dist: urllib3
Requires-Dist: xmljson
Provides-Extra: bs4
Requires-Dist: beautifulsoup4 ; extra == 'bs4'
Requires-Dist: lxml ; extra == 'bs4'
